zhxg_mcp_server/__init__.py
zhxg_mcp_server/__main__.py
zhxg_mcp_server/server.py
zhxg_mcp_server-0.2.2.dist-info/METADATA
zhxg_mcp_server-0.2.2.dist-info/WHEEL
zhxg_mcp_server-0.2.2.dist-info/entry_points.txt
zhxg_mcp_server-0.2.2.dist-info/top_level.txt
zhxg_mcp_server-0.2.2.dist-info/RECORD
