Metadata-Version: 2.4
Name: zhxg-mcp-server
Version: 0.2.2
Summary: 智慧星光 MCP Server
Requires-Python: >=3.10
Requires-Dist: aiohttp>=3.11.18
Requires-Dist: argparse>=1.4.0
Requires-Dist: logging>=0.4.9.6
Requires-Dist: mcp>=1.9.0
Requires-Dist: pydantic>=2.11.4
Requires-Dist: typing>=3.10.0.0
